{"updated":"2026-06-10 19:10","updated_ts":1781089811,"sw_l1":[{"code":"801010","name":"农林牧渔","pct":0.32,"date":"2026-06-10","open":2318.56,"high":2347.51,"low":2316.3,"close":2337.51,"prev_close":2330.07,"vol":17.11},{"code":"801030","name":"基础化工","pct":0.65,"date":"2026-06-10","open":4516.54,"high":4585.35,"low":4515.15,"close":4561.59,"prev_close":4532.32,"vol":83.16},{"code":"801040","name":"钢铁","pct":-0.98,"date":"2026-06-10","open":2279.91,"high":2297.51,"low":2255.7,"close":2275.63,"prev_close":2298.22,"vol":21.15},{"code":"801050","name":"有色金属","pct":-1.59,"date":"2026-06-10","open":8185.09,"high":8301.41,"low":8121.19,"close":8229.35,"prev_close":8361.96,"vol":63.52},{"code":"801080","name":"电子","pct":-2.23,"date":"2026-06-10","open":9449.73,"high":9638.42,"low":9231.72,"close":9351.84,"prev_close":9565.15,"vol":194.07},{"code":"801880","name":"汽车","pct":-2.91,"date":"2026-06-10","open":7158.26,"high":7158.26,"low":6976.75,"close":7024.03,"prev_close":7234.61,"vol":45.98},{"code":"801110","name":"家用电器","pct":-0.15,"date":"2026-06-10","open":8788.0,"high":8851.05,"low":8737.84,"close":8803.74,"prev_close":8816.84,"vol":13.29},{"code":"801120","name":"食品饮料","pct":1.2,"date":"2026-06-10","open":13798.99,"high":14045.36,"low":13794.73,"close":14008.14,"prev_close":13842.03,"vol":16.29},{"code":"801130","name":"纺织服饰","pct":-0.86,"date":"2026-06-10","open":1530.99,"high":1537.12,"low":1512.22,"close":1525.43,"prev_close":1538.68,"vol":11.08},{"code":"801140","name":"轻工制造","pct":-0.76,"date":"2026-06-10","open":2229.59,"high":2235.84,"low":2197.44,"close":2222.85,"prev_close":2239.95,"vol":22.13},{"code":"801150","name":"医药生物","pct":0.32,"date":"2026-06-10","open":6960.53,"high":7018.44,"low":6912.46,"close":7017.46,"prev_close":6995.32,"vol":43.66},{"code":"801160","name":"公用事业","pct":-1.99,"date":"2026-06-10","open":2689.72,"high":2689.72,"low":2645.12,"close":2656.41,"prev_close":2710.45,"vol":82.76},{"code":"801170","name":"交通运输","pct":0.09,"date":"2026-06-10","open":2042.82,"high":2053.39,"low":2037.2,"close":2052.72,"prev_close":2050.91,"vol":32.19},{"code":"801180","name":"房地产","pct":-0.27,"date":"2026-06-10","open":1931.28,"high":1946.94,"low":1924.97,"close":1942.23,"prev_close":1947.41,"vol":40.04},{"code":"801200","name":"商贸零售","pct":-1.21,"date":"2026-06-10","open":1854.75,"high":1854.75,"low":1827.49,"close":1838.96,"prev_close":1861.42,"vol":24.14},{"code":"801210","name":"社会服务","pct":-0.06,"date":"2026-06-10","open":7516.13,"high":7570.61,"low":7503.36,"close":7560.38,"prev_close":7564.74,"vol":12.46},{"code":"801780","name":"银行","pct":1.51,"date":"2026-06-10","open":3998.36,"high":4066.43,"low":3994.42,"close":4058.67,"prev_close":3998.1,"vol":44.2},{"code":"801790","name":"非银金融","pct":0.78,"date":"2026-06-10","open":1649.82,"high":1684.42,"low":1649.61,"close":1682.78,"prev_close":1669.71,"vol":39.25},{"code":"801230","name":"综合","pct":-1.46,"date":"2026-06-10","open":4441.59,"high":4460.68,"low":4379.1,"close":4440.53,"prev_close":4506.43,"vol":4.8},{"code":"801710","name":"建筑材料","pct":-1.23,"date":"2026-06-10","open":6469.07,"high":6507.71,"low":6330.89,"close":6410.88,"prev_close":6490.5,"vol":24.71},{"code":"801720","name":"建筑装饰","pct":-0.54,"date":"2026-06-10","open":2040.06,"high":2048.93,"low":2026.94,"close":2043.49,"prev_close":2054.52,"vol":44.91},{"code":"801730","name":"电力设备","pct":-2.63,"date":"2026-06-10","open":10628.85,"high":10635.18,"low":10330.4,"close":10480.99,"prev_close":10763.99,"vol":96.9},{"code":"801890","name":"机械设备","pct":-3.0,"date":"2026-06-10","open":2517.56,"high":2517.61,"low":2438.92,"close":2472.07,"prev_close":2548.57,"vol":89.95},{"code":"801740","name":"国防军工","pct":-0.89,"date":"2026-06-10","open":1778.38,"high":1798.92,"low":1753.27,"close":1773.28,"prev_close":1789.28,"vol":23.69},{"code":"801750","name":"计算机","pct":-1.76,"date":"2026-06-10","open":4578.82,"high":4654.9,"low":4496.83,"close":4535.63,"prev_close":4616.81,"vol":63.41},{"code":"801760","name":"传媒","pct":-1.07,"date":"2026-06-10","open":703.78,"high":714.66,"low":699.26,"close":703.66,"prev_close":711.28,"vol":44.41},{"code":"801770","name":"通信","pct":-2.75,"date":"2026-06-10","open":8869.99,"high":8999.73,"low":8723.72,"close":8804.55,"prev_close":9053.73,"vol":40.54},{"code":"801950","name":"煤炭","pct":-3.24,"date":"2026-06-10","open":3407.93,"high":3412.94,"low":3305.38,"close":3319.79,"prev_close":3430.82,"vol":28.04},{"code":"801960","name":"石油石化","pct":-0.86,"date":"2026-06-10","open":2590.05,"high":2609.34,"low":2561.32,"close":2578.27,"prev_close":2600.56,"vol":18.14},{"code":"801970","name":"环保","pct":-0.57,"date":"2026-06-10","open":2029.63,"high":2038.41,"low":2006.96,"close":2034.63,"prev_close":2046.2,"vol":19.01},{"code":"801980","name":"美容护理","pct":0.29,"date":"2026-06-10","open":3443.91,"high":3469.61,"low":3405.17,"close":3467.48,"prev_close":3457.38,"vol":1.53}],"industry":[{"code":"BK1318","name":"光伏主材","price":12014.34,"pct":7.44,"chg":832.19,"vol":169591980000,"flow":213585840.0},{"code":"BK1325","name":"半导体材料","price":13637.53,"pct":4.36,"chg":570.21,"vol":1100230304000,"flow":2270440448.0},{"code":"BK1562","name":"人工景区","price":2784.69,"pct":3.99,"chg":106.79,"vol":34689671000,"flow":126906917.0},{"code":"BK1577","name":"啤酒","price":2617.03,"pct":3.86,"chg":97.35,"vol":169755741000,"flow":142956187.0},{"code":"BK1424","name":"氟化工","price":14486.05,"pct":3.62,"chg":505.52,"vol":333639232000,"flow":535745936.0},{"code":"BK1443","name":"橡胶助剂","price":4742.55,"pct":3.61,"chg":165.23,"vol":42776092000,"flow":149512251.0},{"code":"BK1365","name":"租赁","price":2838.83,"pct":3.53,"chg":96.8,"vol":73852014000,"flow":8702700.0},{"code":"BK1412","name":"氨纶","price":2599.65,"pct":3.4,"chg":85.57,"vol":51263078000,"flow":11227550.0},{"code":"BK1358","name":"保险Ⅲ","price":1268.17,"pct":3.19,"chg":39.25,"vol":2736118688000,"flow":964996832.0},{"code":"BK0474","name":"保险Ⅱ","price":1268.17,"pct":3.19,"chg":39.25,"vol":2736118688000,"flow":964996832.0},{"code":"BK1295","name":"其他数字媒体","price":1319.01,"pct":2.92,"chg":37.39,"vol":14346726000,"flow":-95568240.0},{"code":"BK1564","name":"体育Ⅲ","price":1037.96,"pct":2.57,"chg":25.99,"vol":11445121000,"flow":39500203.0},{"code":"BK1273","name":"体育Ⅱ","price":1037.96,"pct":2.57,"chg":25.99,"vol":11445121000,"flow":39500203.0},{"code":"BK1563","name":"自然景区","price":2981.35,"pct":2.55,"chg":74.16,"vol":61047941000,"flow":88948834.0},{"code":"BK1272","name":"旅游及景区","price":2998.06,"pct":2.47,"chg":72.14,"vol":133909847000,"flow":304010147.0},{"code":"BK1584","name":"熟食","price":2313.39,"pct":2.39,"chg":54.08,"vol":24310957000,"flow":-7903740.0},{"code":"BK1609","name":"城商行Ⅲ","price":1600.81,"pct":2.13,"chg":33.43,"vol":1300395168000,"flow":-553384176.0},{"code":"BK1587","name":"电信运营商","price":1018.31,"pct":2.01,"chg":20.11,"vol":2820359696000,"flow":213893200.0},{"code":"BK1431","name":"有机硅","price":3528.02,"pct":1.97,"chg":68.17,"vol":116929333000,"flow":47650560.0},{"code":"BK1283","name":"银行","price":4194.1,"pct":1.91,"chg":78.45,"vol":15519036416000,"flow":587610368.0},{"code":"BK0475","name":"银行Ⅱ","price":4194.1,"pct":1.91,"chg":78.45,"vol":15519036416000,"flow":587610368.0},{"code":"BK1625","name":"钨","price":9571.49,"pct":1.9,"chg":178.22,"vol":315745888000,"flow":717629456.0},{"code":"BK1612","name":"农商行Ⅲ","price":459.81,"pct":1.87,"chg":8.43,"vol":268633296000,"flow":16323887.0},{"code":"BK1512","name":"生猪养殖","price":3569.41,"pct":1.87,"chg":65.37,"vol":393329760000,"flow":100412288.0},{"code":"BK1610","name":"股份制银行Ⅲ","price":2351.29,"pct":1.78,"chg":41.21,"vol":2889181072000,"flow":884072576.0},{"code":"BK1279","name":"非白酒","price":2074.95,"pct":1.71,"chg":34.83,"vol":231104886000,"flow":153070399.0},{"code":"BK1500","name":"医美耗材","price":1435.57,"pct":1.58,"chg":22.36,"vol":62654526000,"flow":11041033.0},{"code":"BK1438","name":"合成树脂","price":9027.39,"pct":1.57,"chg":139.55,"vol":192688409000,"flow":255060144.0},{"code":"BK1428","name":"其他化学制品","price":4504.8,"pct":1.54,"chg":68.23,"vol":515632224000,"flow":652524304.0},{"code":"BK1611","name":"国有大型银行Ⅲ","price":3139.73,"pct":1.51,"chg":46.68,"vol":11060827136000,"flow":240598032.0},{"code":"BK1426","name":"聚氨酯","price":3584.78,"pct":1.5,"chg":53.0,"vol":247413643000,"flow":-38173984.0},{"code":"BK1561","name":"旅游综合","price":1704.6,"pct":1.37,"chg":23.12,"vol":38172234000,"flow":88154381.0},{"code":"BK1420","name":"其他化学原料","price":3226.88,"pct":1.3,"chg":41.39,"vol":172006021000,"flow":353420352.0},{"code":"BK1489","name":"快递","price":5174.02,"pct":1.27,"chg":64.93,"vol":282280336000,"flow":136145957.0},{"code":"BK1366","name":"证券Ⅲ","price":129730.39,"pct":1.13,"chg":1444.26,"vol":3345228800000,"flow":1271438592.0},{"code":"BK0473","name":"证券Ⅱ","price":129730.39,"pct":1.13,"chg":1444.26,"vol":3345228800000,"flow":1271438592.0},{"code":"BK1326","name":"半导体设备","price":45555.09,"pct":1.09,"chg":491.43,"vol":1771883584000,"flow":1976740096.0},{"code":"BK1332","name":"电子化学品Ⅲ","price":3703.08,"pct":1.05,"chg":38.38,"vol":786220080000,"flow":-669896704.0},{"code":"BK1039","name":"电子化学品Ⅱ","price":3703.08,"pct":1.05,"chg":38.38,"vol":786220080000,"flow":-669896704.0},{"code":"BK1422","name":"无机盐","price":3221.87,"pct":1.02,"chg":32.62,"vol":145569521000,"flow":426629328.0},{"code":"BK1401","name":"纺织服装设备","price":3953.86,"pct":1.0,"chg":39.14,"vol":90048821000,"flow":80759419.0},{"code":"BK1549","name":"旅游零售Ⅲ","price":6462.11,"pct":0.99,"chg":63.16,"vol":130041124000,"flow":123039584.0},{"code":"BK1269","name":"旅游零售Ⅱ","price":6462.11,"pct":0.99,"chg":63.16,"vol":130041124000,"flow":123039584.0},{"code":"BK1568","name":"人力资源服务","price":1835.09,"pct":0.96,"chg":17.48,"vol":21965211000,"flow":-21820308.0},{"code":"BK1606","name":"线下药店","price":3341.75,"pct":0.96,"chg":31.69,"vol":76597023000,"flow":-73340907.0},{"code":"BK1203","name":"非银金融","price":2284.28,"pct":0.91,"chg":20.6,"vol":6586493184000,"flow":2205707520.0},{"code":"BK1439","name":"膜材料","price":4280.76,"pct":0.9,"chg":38.24,"vol":273947712000,"flow":-694112240.0},{"code":"BK0538","name":"化学制品","price":32900.59,"pct":0.89,"chg":290.63,"vol":1790178032000,"flow":954109184.0},{"code":"BK1425","name":"胶黏剂及胶带","price":3485.26,"pct":0.88,"chg":30.28,"vol":26752903000,"flow":-76796336.0},{"code":"BK1259","name":"养殖业","price":3477.72,"pct":0.86,"chg":29.5,"vol":465242032000,"flow":115769904.0},{"code":"BK1501","name":"动物保健Ⅲ","price":4110.32,"pct":0.86,"chg":34.86,"vol":59691395000,"flow":7727167.0},{"code":"BK1254","name":"动物保健Ⅱ","price":4110.32,"pct":0.86,"chg":34.86,"vol":59691395000,"flow":7727167.0},{"code":"BK1450","name":"空调","price":14322.53,"pct":0.79,"chg":112.63,"vol":889633920000,"flow":124910016.0},{"code":"BK1456","name":"其他家电Ⅲ","price":1152.98,"pct":0.79,"chg":8.99,"vol":10132653000,"flow":5996019.0},{"code":"BK1243","name":"其他家电Ⅱ","price":1152.98,"pct":0.79,"chg":8.99,"vol":10132653000,"flow":5996019.0},{"code":"BK1511","name":"肉鸡养殖","price":3096.6,"pct":0.77,"chg":23.72,"vol":63791198000,"flow":22012629.0},{"code":"BK1290","name":"教育出版","price":2042.27,"pct":0.73,"chg":14.79,"vol":122376539000,"flow":-9289045.0},{"code":"BK1430","name":"涂料油墨","price":3844.84,"pct":0.69,"chg":26.3,"vol":83074986000,"flow":57251218.0},{"code":"BK1515","name":"粮食种植","price":961.22,"pct":0.63,"chg":6.02,"vol":36560968000,"flow":-27625108.0},{"code":"BK1560","name":"酒店","price":2229.35,"pct":0.62,"chg":13.81,"vol":45175537000,"flow":-28927773.0},{"code":"BK1019","name":"化学原料","price":1024.24,"pct":0.57,"chg":5.77,"vol":817883872000,"flow":670673888.0},{"code":"BK1418","name":"氯碱","price":2077.4,"pct":0.55,"chg":11.4,"vol":149698604000,"flow":135524716.0},{"code":"BK1435","name":"磷肥及磷化工","price":2942.06,"pct":0.54,"chg":15.88,"vol":191870423000,"flow":18696736.0},{"code":"BK1253","name":"医疗美容","price":1073.98,"pct":0.53,"chg":5.69,"vol":68642626000,"flow":-1504343.0},{"code":"BK1582","name":"烘焙食品","price":722.43,"pct":0.53,"chg":3.79,"vol":40127705000,"flow":11887170.0},{"code":"BK1627","name":"综合Ⅲ","price":11861.82,"pct":0.53,"chg":61.95,"vol":202311517000,"flow":-192343008.0},{"code":"BK1217","name":"综合","price":11861.82,"pct":0.53,"chg":61.95,"vol":202311517000,"flow":-192343008.0},{"code":"BK0539","name":"综合Ⅱ","price":11861.82,"pct":0.53,"chg":61.95,"vol":202311517000,"flow":-192343008.0},{"code":"BK1218","name":"出版","price":1897.14,"pct":0.52,"chg":9.82,"vol":248453025000,"flow":351202176.0},{"code":"BK1479","name":"航空运输","price":1396.56,"pct":0.5,"chg":6.97,"vol":455950848000,"flow":-57615200.0},{"code":"BK0420","name":"航空机场","price":4241.74,"pct":0.48,"chg":20.36,"vol":589554912000,"flow":-89785440.0},{"code":"BK1485","name":"铁路运输","price":1508.65,"pct":0.46,"chg":6.92,"vol":402564480000,"flow":-17585834.0},{"code":"BK1480","name":"机场","price":1790.82,"pct":0.45,"chg":7.99,"vol":133604065000,"flow":-32170242.0},{"code":"BK1509","name":"水产饲料","price":5615.05,"pct":0.45,"chg":24.96,"vol":85191267000,"flow":23173066.0},{"code":"BK0454","name":"塑料","price":23156.22,"pct":0.42,"chg":97.66,"vol":772422864000,"flow":-695124736.0},{"code":"BK1600","name":"医疗研发外包","price":5913.15,"pct":0.42,"chg":24.61,"vol":602217296000,"flow":80517536.0},{"code":"BK1289","name":"大众出版","price":1716.16,"pct":0.4,"chg":6.91,"vol":126076485000,"flow":360491216.0},{"code":"BK1292","name":"广告媒体","price":2238.69,"pct":0.38,"chg":8.46,"vol":85300890000,"flow":-76616497.0},{"code":"BK1281","name":"休闲食品","price":2123.7,"pct":0.38,"chg":7.99,"vol":162864901000,"flow":-27573351.0},{"code":"BK1598","name":"疫苗","price":3699.69,"pct":0.38,"chg":13.83,"vol":200590079000,"flow":-30414141.0},{"code":"BK1376","name":"核力发电","price":628.45,"pct":0.37,"chg":2.32,"vol":501919600000,"flow":71321175.0},{"code":"BK1345","name":"商业地产","price":1241.12,"pct":0.37,"chg":4.57,"vol":202065166000,"flow":-83097929.0},{"code":"BK1576","name":"调味发酵品Ⅲ","price":4675.37,"pct":0.33,"chg":15.59,"vol":342848080000,"flow":-238332896.0},{"code":"BK1278","name":"调味发酵品Ⅱ","price":4675.37,"pct":0.33,"chg":15.59,"vol":342848080000,"flow":-238332896.0},{"code":"BK1206","name":"基础化工","price":3749.16,"pct":0.33,"chg":12.19,"vol":4864989184000,"flow":317389312.0},{"code":"BK1565","name":"会展服务","price":1068.34,"pct":0.31,"chg":3.33,"vol":14623246000,"flow":7668157.0},{"code":"BK1571","name":"油品石化贸易","price":3157.78,"pct":0.31,"chg":9.69,"vol":29179967000,"flow":8649361.0},{"code":"BK1437","name":"改性塑料","price":7509.52,"pct":0.24,"chg":18.35,"vol":174082867000,"flow":-282009968.0},{"code":"BK1618","name":"磁性材料","price":6340.96,"pct":0.23,"chg":14.48,"vol":220132392000,"flow":555078784.0},{"code":"BK1495","name":"生活用纸","price":1085.58,"pct":0.23,"chg":2.47,"vol":50881291000,"flow":-2515821.0},{"code":"BK1578","name":"其他酒类","price":1509.84,"pct":0.2,"chg":2.98,"vol":61349145000,"flow":10114226.0},{"code":"BK1575","name":"白酒Ⅲ","price":4156.63,"pct":0.18,"chg":7.44,"vol":2437643776000,"flow":173452576.0},{"code":"BK1277","name":"白酒Ⅱ","price":4156.63,"pct":0.18,"chg":7.44,"vol":2437643776000,"flow":173452576.0},{"code":"BK1483","name":"高速公路","price":2656.0,"pct":0.18,"chg":4.73,"vol":372876720000,"flow":-72561413.0},{"code":"BK1419","name":"煤化工","price":1683.83,"pct":0.16,"chg":2.71,"vol":237948189000,"flow":-226334940.0},{"code":"BK1271","name":"酒店餐饮","price":2131.02,"pct":0.16,"chg":3.37,"vol":56609602000,"flow":-39752592.0},{"code":"BK1328","name":"集成电路封测","price":9215.86,"pct":0.15,"chg":13.52,"vol":439390032000,"flow":-2400160512.0},{"code":"BK1508","name":"畜禽饲料","price":1778.96,"pct":0.13,"chg":2.27,"vol":50222581000,"flow":-21760041.0},{"code":"BK0438","name":"食品饮料","price":25835.38,"pct":0.12,"chg":31.9,"vol":3831441552000,"flow":-93867488.0},{"code":"BK1462","name":"玻纤制造","price":17792.44,"pct":0.12,"chg":21.01,"vol":596773568000,"flow":-243644080.0}],"concept":[],"geo":[{"code":"BK0163","name":"青海板块","price":6824.35,"pct":-0.24,"chg":-16.68,"vol":440937216000,"flow":59350992.0},{"code":"BK0174","name":"西藏板块","price":23158.9,"pct":-0.4,"chg":-94.13,"vol":273172752000,"flow":-88248304.0},{"code":"BK0146","name":"黑龙江","price":7842.98,"pct":-0.54,"chg":-42.32,"vol":370618288000,"flow":-348131232.0},{"code":"BK0162","name":"宁夏板块","price":9631.66,"pct":-0.63,"chg":-61.04,"vol":268731760000,"flow":-112088400.0},{"code":"BK0173","name":"贵州板块","price":32222.68,"pct":-0.71,"chg":-230.17,"vol":1940589584000,"flow":338096160.0},{"code":"BK0175","name":"内蒙古","price":24924.88,"pct":-0.73,"chg":-184.27,"vol":1023742384000,"flow":-1015793152.0},{"code":"BK0166","name":"天津板块","price":14534.61,"pct":-0.76,"chg":-111.65,"vol":1971240864000,"flow":648269312.0},{"code":"BK0148","name":"吉林板块","price":20267.28,"pct":-0.83,"chg":-169.25,"vol":376605728000,"flow":-395451424.0},{"code":"BK0152","name":"甘肃板块","price":19011.84,"pct":-0.91,"chg":-174.53,"vol":375373872000,"flow":-525050736.0},{"code":"BK0164","name":"山东板块","price":21184.73,"pct":-0.91,"chg":-194.72,"vol":5963948800000,"flow":-4757478144.0},{"code":"BK0147","name":"新疆板块","price":20589.27,"pct":-0.92,"chg":-192.01,"vol":943730640000,"flow":-1344179088.0},{"code":"BK0169","name":"四川板块","price":25593.57,"pct":-0.94,"chg":-242.66,"vol":3581461648000,"flow":-294152448.0},{"code":"BK0170","name":"重庆板块","price":19056.76,"pct":-0.99,"chg":-191.48,"vol":1095372976000,"flow":-336663936.0},{"code":"BK0145","name":"上海板块","price":22052.7,"pct":-1.02,"chg":-227.78,"vol":10232753408000,"flow":-5362927360.0},{"code":"BK0150","name":"北京板块","price":9638.73,"pct":-1.1,"chg":-107.45,"vol":28762891776000,"flow":-9402565632.0},{"code":"BK0161","name":"辽宁板块","price":20939.21,"pct":-1.13,"chg":-238.67,"vol":1135969360000,"flow":-628098816.0},{"code":"BK0171","name":"云南板块","price":18081.33,"pct":-1.14,"chg":-207.84,"vol":936751808000,"flow":-1192927888.0},{"code":"BK0155","name":"河北板块","price":17143.8,"pct":-1.25,"chg":-216.24,"vol":1689197312000,"flow":-739146752.0},{"code":"BK0176","name":"海南板块","price":8478.47,"pct":-1.25,"chg":-107.52,"vol":498124640000,"flow":84254336.0},{"code":"BK0149","name":"安徽板块","price":29259.97,"pct":-1.29,"chg":-381.32,"vol":2664543360000,"flow":-3676045568.0},{"code":"BK0151","name":"福建板块","price":24819.35,"pct":-1.34,"chg":-336.81,"vol":5404164352000,"flow":-5205364224.0},{"code":"BK0160","name":"江西板块","price":41651.32,"pct":-1.39,"chg":-587.45,"vol":1337100592000,"flow":-1453181696.0},{"code":"BK0172","name":"浙江板块","price":29901.03,"pct":-1.41,"chg":-426.97,"vol":9414527232000,"flow":-8728410112.0},{"code":"BK0159","name":"江苏板块","price":34441.15,"pct":-1.52,"chg":-531.92,"vol":10810932480000,"flow":-19532034304.0},{"code":"BK0153","name":"广东板块","price":45354.75,"pct":-1.52,"chg":-701.56,"vol":21234216192000,"flow":-25344524288.0},{"code":"BK0165","name":"陕西板块","price":18900.07,"pct":-1.52,"chg":-292.51,"vol":2013165488000,"flow":-2716654336.0},{"code":"BK0154","name":"广西板块","price":9766.93,"pct":-1.55,"chg":-153.72,"vol":419413136000,"flow":-317760448.0},{"code":"BK0158","name":"湖南板块","price":26062.95,"pct":-1.59,"chg":-421.62,"vol":1914481488000,"flow":-2077735424.0},{"code":"BK0157","name":"湖北板块","price":22057.31,"pct":-1.68,"chg":-376.36,"vol":2757395328000,"flow":-6776757504.0},{"code":"BK0156","name":"河南板块","price":21869.34,"pct":-1.96,"chg":-438.27,"vol":2002390912000,"flow":-2999779840.0},{"code":"BK0167","name":"山西板块","price":11651.29,"pct":-2.32,"chg":-276.4,"vol":735119440000,"flow":-1014562896.0}]}